odoo/addons/l10n_ch_states/README.rst
odoo/addons/l10n_ch_states/__init__.py
odoo/addons/l10n_ch_states/__manifest__.py
odoo/addons/l10n_ch_states/data/res_country_states.xml
odoo/addons/l10n_ch_states/i18n/de.po
odoo/addons/l10n_ch_states/i18n/fr.po
odoo/addons/l10n_ch_states/i18n/it.po
odoo/addons/l10n_ch_states/i18n/l10n_ch_states.pot
odoo/addons/l10n_ch_states/models/__init__.py
odoo/addons/l10n_ch_states/models/res_country.py
odoo/addons/l10n_ch_states/readme/CONTRIBUTORS.rst
odoo/addons/l10n_ch_states/readme/DESCRIPTION.rst
odoo/addons/l10n_ch_states/readme/USAGE.rst
odoo/addons/l10n_ch_states/static/description/icon.png
odoo/addons/l10n_ch_states/static/description/index.html
odoo13_addon_l10n_ch_states-13.0.1.0.1.dev4.dist-info/METADATA
odoo13_addon_l10n_ch_states-13.0.1.0.1.dev4.dist-info/WHEEL
odoo13_addon_l10n_ch_states-13.0.1.0.1.dev4.dist-info/top_level.txt
odoo13_addon_l10n_ch_states-13.0.1.0.1.dev4.dist-info/RECORD
